mavis_config/__init__.py
mavis_config/config.json
mavis_config/constants.py
mavis_config/overlay.json
mavis_temp-2.0.0.data/data/mavis_config/config.json
mavis_temp-2.0.0.data/data/mavis_config/overlay.json
mavis_temp-2.0.0.dist-info/LICENSE
mavis_temp-2.0.0.dist-info/METADATA
mavis_temp-2.0.0.dist-info/WHEEL
mavis_temp-2.0.0.dist-info/top_level.txt
mavis_temp-2.0.0.dist-info/RECORD
